dkfoldermanager/__init__.py
dkfoldermanager/dkfoldermanager.py
DkFolderManager-0.0.1.dist-info/METADATA
DkFolderManager-0.0.1.dist-info/WHEEL
DkFolderManager-0.0.1.dist-info/top_level.txt
DkFolderManager-0.0.1.dist-info/RECORD
