Metadata-Version: 2.1
Name: DkFolderManager
Version: 0.0.1
Summary: A simple folder management library using JSON
Author: dntjd207
Author-email: dntjd207@naver.com
Classifier: Programming Language :: Python :: 3
Classifier: License :: OSI Approved :: MIT License
Classifier: Operating System :: OS Independent
Requires-Python: >=3.6
